{
  "video_id": "1MvpwiGQmIs",
  "title": "每日國際新聞｜法國推兒童社交媒體禁令、無人機令烏克蘭傷亡升37%，｜Simon Universe",
  "published": "2026-07-22T10:30:05+00:00",
  "url": "https://www.youtube.com/watch?v=1MvpwiGQmIs",
  "data": {
    "tldr": "今日國際新聞聚焦美伊衝突持續升級、胡塞武裝封鎖沙特港口威脅紅海航運，以及川普對加國加徵五成關稅衝擊北美自由貿易。",
    "summary": "本期國際新聞簡報涵蓋多項關鍵地緣政治與經濟動態。首先，中東局勢顯著惡化，美軍對伊拉克及敘利亞境內親伊武裝發動連續第十一晚空襲，德黑蘭則以飛彈和無人機反擊美軍海灣基地，戰事已演變為長期消耗戰。與此同時，葉門胡塞武裝宣布封鎖沙特阿拉伯港口，使紅海航運風險從商船襲擊擴大至能源出口威脅，恐與霍爾木茲海峽危機產生共振效應。\n\n在貿易政策方面，美國總統川普簽署公告，準備對部分加拿大進口商品加徵高達五成的關稅，涉及酒類、水泥及關鍵礦產等，嚴重衝擊北美免稅貿易框架。此外，聯合國報告指出，烏克蘭平民因長程導彈及短程無人機襲擊，傷亡人數同比激增三成七；而匈牙利檢察部門搜查前總理歐爾班政黨辦公室，則使國家基金案演變成對該國法治重建的嚴峻考驗。",
    "highlights": [
      "美伊衝突進入第十一晚空襲與反擊，戰事由有限度懲罰轉為高消耗的長期對抗。",
      "胡塞武裝宣布封鎖沙特港口，紅海航運與能源出口面臨與霍爾木茲海峽危機共振的雙重威脅。",
      "川普簽署公告擬對加拿大酒類、水泥等商品加徵五成關稅，衝擊北美供應鏈與免稅框架。",
      "聯合國監察團指出，烏克蘭平民傷亡因無人機與導彈襲擊同比增加37%，短程無人機成新致命威脅。",
      "匈牙利檢察部門搜查 Fidesz 黨部，調查涉及逾170億福林的國家文化基金撥款案。"
    ],
    "key_concepts": [
      {
        "term": "消耗戰 (War of Attrition)",
        "explanation": "雙方企圖通過長期、持續的人員與物資消耗，來疲憊並擊垮對手的戰爭形式。"
      },
      {
        "term": "北美免稅框架 (North American Duty-Free Framework)",
        "explanation": "美加墨三國間建立的免稅貿易協定，旨在促進區域內供應鏈的深度整合。"
      },
      {
        "term": "法治考驗 (Rule of Law Test)",
        "explanation": "評估司法機關能否獨立於行政干預，公正調查涉及執政核心人物的案件。"
      }
    ],
    "why_it_matters": "中東軍事衝突的常態化與北美貿易壁壘的重塑，正加速全球供應鏈碎片化，並對能源安全與地緣政治穩定帶來深遠衝擊。"
  },
  "markdown": "# 每日國際新聞｜法國推兒童社交媒體禁令、無人機令烏克蘭傷亡升37%，｜Simon Universe\n\n**Channel:** Simon Universe丨國際關係教室  \n**Published:** 2026-07-22  \n**Link:** https://www.youtube.com/watch?v=1MvpwiGQmIs\n\n> **The Gist** — 今日國際新聞聚焦美伊衝突持續升級、胡塞武裝封鎖沙特港口威脅紅海航運，以及川普對加國加徵五成關稅衝擊北美自由貿易。\n\n## Summary\n\n本期國際新聞簡報涵蓋多項關鍵地緣政治與經濟動態。首先，中東局勢顯著惡化，美軍對伊拉克及敘利亞境內親伊武裝發動連續第十一晚空襲，德黑蘭則以飛彈和無人機反擊美軍海灣基地，戰事已演變為長期消耗戰。與此同時，葉門胡塞武裝宣布封鎖沙特阿拉伯港口，使紅海航運風險從商船襲擊擴大至能源出口威脅，恐與霍爾木茲海峽危機產生共振效應。\n\n在貿易政策方面，美國總統川普簽署公告，準備對部分加拿大進口商品加徵高達五成的關稅，涉及酒類、水泥及關鍵礦產等，嚴重衝擊北美免稅貿易框架。此外，聯合國報告指出，烏克蘭平民因長程導彈及短程無人機襲擊，傷亡人數同比激增三成七；而匈牙利檢察部門搜查前總理歐爾班政黨辦公室，則使國家基金案演變成對該國法治重建的嚴峻考驗。\n\n## Highlights\n\n- 美伊衝突進入第十一晚空襲與反擊，戰事由有限度懲罰轉為高消耗的長期對抗。\n- 胡塞武裝宣布封鎖沙特港口，紅海航運與能源出口面臨與霍爾木茲海峽危機共振的雙重威脅。\n- 川普簽署公告擬對加拿大酒類、水泥等商品加徵五成關稅，衝擊北美供應鏈與免稅框架。\n- 聯合國監察團指出，烏克蘭平民傷亡因無人機與導彈襲擊同比增加37%，短程無人機成新致命威脅。\n- 匈牙利檢察部門搜查 Fidesz 黨部，調查涉及逾170億福林的國家文化基金撥款案。\n\n## Key Concepts\n\n- **消耗戰 (War of Attrition)** — 雙方企圖通過長期、持續的人員與物資消耗，來疲憊並擊垮對手的戰爭形式。\n- **北美免稅框架 (North American Duty-Free Framework)** — 美加墨三國間建立的免稅貿易協定，旨在促進區域內供應鏈的深度整合。\n- **法治考驗 (Rule of Law Test)** — 評估司法機關能否獨立於行政干預，公正調查涉及執政核心人物的案件。\n\n## Why It Matters\n\n中東軍事衝突的常態化與北美貿易壁壘的重塑，正加速全球供應鏈碎片化，並對能源安全與地緣政治穩定帶來深遠衝擊。\n"
}